MANIFEST.in
README.md
setup.py
pyppeteer_stealth/__init__.py
pyppeteer_stealth/chrome_app.py
pyppeteer_stealth/chrome_runtime.py
pyppeteer_stealth/iframe_content_window.py
pyppeteer_stealth/media_codecs.py
pyppeteer_stealth/navigator_hardware_concurrency.py
pyppeteer_stealth/navigator_languages.py
pyppeteer_stealth/navigator_permissions.py
pyppeteer_stealth/navigator_plugins.py
pyppeteer_stealth/navigator_vendor.py
pyppeteer_stealth/navigator_webdriver.py
pyppeteer_stealth/sourceurl.py
pyppeteer_stealth/user_agent_override.py
pyppeteer_stealth/utils.py
pyppeteer_stealth/webgl_vendor.py
pyppeteer_stealth/window_outerdimensions.py
pyppeteer_stealth.egg-info/PKG-INFO
pyppeteer_stealth.egg-info/SOURCES.txt
pyppeteer_stealth.egg-info/dependency_links.txt
pyppeteer_stealth.egg-info/top_level.txt
pyppeteer_stealth/js/chrome.app.js
pyppeteer_stealth/js/chrome.csi.js
pyppeteer_stealth/js/chrome.loadTimes.js
pyppeteer_stealth/js/chrome.runtime.js
pyppeteer_stealth/js/iframe.contentWindow.js
pyppeteer_stealth/js/media.codecs.js
pyppeteer_stealth/js/navigator.hardwareConcurrency.js
pyppeteer_stealth/js/navigator.languages.js
pyppeteer_stealth/js/navigator.permissions.js
pyppeteer_stealth/js/navigator.plugins.js
pyppeteer_stealth/js/navigator.vendor.js
pyppeteer_stealth/js/navigator.webdriver.js
pyppeteer_stealth/js/utils.js
pyppeteer_stealth/js/webgl.vendor.js
pyppeteer_stealth/js/window.outerdimensions.js