Metadata-Version: 2.1
Name: pyppeteer-stealth
Version: 2.7.2
Summary: pyppeteer stealth
Home-page: https://github.com/MeiK2333/pyppeteer-stealth
Author: MeiK2333
Author-email: meik2333@gmail.com
License: UNKNOWN
Platform: UNKNOWN
